united_states/__init__.py
united_states/__main__.py
united_states/frozenlist.py
united_states/geometry.py
united_states/py.typed
united_states/shapes.zip
these_united_states-1.2.0.24.dist-info/METADATA
these_united_states-1.2.0.24.dist-info/WHEEL
these_united_states-1.2.0.24.dist-info/licenses/LICENSE
these_united_states-1.2.0.24.dist-info/RECORD
