Metadata-Version: 2.4
Name: these-united-states
Version: 1.2.0.24
Summary: Utility library for performing reverse geocoding of states in the United States of America
Project-URL: Source Code, https://github.com/avantus-tech/these-united-states
Author-email: Brandon Carpenter <brandon@avantus.com>
License-Expression: BSD-3-Clause
License-File: LICENSE
Keywords: geocoding,reverse,states
Classifier: Development Status :: 5 - Production/Stable
Classifier: Intended Audience :: Developers
Classifier: Intended Audience :: Science/Research
Classifier: License :: OSI Approved :: BSD License
Classifier: Operating System :: OS Independent
Classifier: Programming Language :: Python :: 3
Classifier: Programming Language :: Python :: 3.9
Classifier: Programming Language :: Python :: 3.10
Classifier: Programming Language :: Python :: 3.11
Classifier: Programming Language :: Python :: 3.12
Classifier: Programming Language :: Python :: 3.13
Classifier: Topic :: Scientific/Engineering :: GIS
Classifier: Typing :: Typed
Requires-Python: >=3.9
Requires-Dist: pyshp!=2.1.1,~=2.0
Provides-Extra: cli
Requires-Dist: click~=8.0; extra == 'cli'
Provides-Extra: plot
Requires-Dist: matplotlib~=3.2; extra == 'plot'
Requires-Dist: pyqt6~=6.8; extra == 'plot'
